passwarrior/__init__.py
passwarrior-0.1.1.dist-info/METADATA
passwarrior-0.1.1.dist-info/WHEEL
passwarrior-0.1.1.dist-info/top_level.txt
passwarrior-0.1.1.dist-info/RECORD
