Metadata-Version: 2.4
Name: passwarrior
Version: 0.1.1
Summary: A simple Python package for generating random passwords
Home-page: https://github.com/C-Shi/passwarrior
Author: Your Name
Author-email: mr.cheng.shi@gmail.com
Classifier: Programming Language :: Python :: 3
Classifier: License :: OSI Approved :: MIT License
Classifier: Operating System :: OS Independent
Requires-Python: >=3.9
Dynamic: author
Dynamic: author-email
Dynamic: classifier
Dynamic: description
Dynamic: description-content-type
Dynamic: home-page
Dynamic: requires-python
Dynamic: summary
